DDriver/__init__.py
DDriver/DDriver.py
ddriver-0.1.0.dist-info/LICENSE
ddriver-0.1.0.dist-info/METADATA
ddriver-0.1.0.dist-info/WHEEL
ddriver-0.1.0.dist-info/RECORD
