Metadata-Version: 2.1
Name: ddriver
Version: 0.1.0
Summary: M542 Driver for raspberry pi
License: Apache 2.0
Author: fulu.song
Author-email: fulu.song@witintech.com
Requires-Python: >=3.9
Classifier: License :: Other/Proprietary License
Classifier: Programming Language :: Python :: 3
Classifier: Programming Language :: Python :: 3.9
Classifier: Programming Language :: Python :: 3.10
Classifier: Programming Language :: Python :: 3.11
Classifier: Programming Language :: Python :: 3.12
Classifier: Programming Language :: Python :: 3.13
